{
  "ATM": 1,
  "Acer": 1,
  "Adelaide": 1,
  "Aedes": 0,
  "Aeneas": 2,
  "Aksobhya": 0,
  "Alabama": 3,
  "Alaska": 1,
  "Amazon": 2,
  "America": 2,
  "Anglo-Saxon": 3,
  "Angus": 1,
  "Antananarivo": 0,
  "Arizona": 1,
  "Arkansas": 1,
  "Ashgabat": 0,
  "Asia": 1,
  "Atlantis": 2,
  "Austria": 2,
  "Bacchus": 0,
  "Bangui": 0,
  "Banjul": 0,
  "Baptists": 1,
  "Barbados": 0,
  "Belarus": 1,
  "Belgrade": 2,
  "Belmopan": 0,
  "Bologna": 0,
  "Bonn": 0,
  "Borrelia": 0,
  "Bosphorus": 0,
  "Brazzaville": 0,
  "Brest": 0,
  "Bridgetown": 0,
  "Buddhism": 1,
  "Bujumbura": 0,
  "COVID-19": 2,
  "California": 1,
  "Canada": 2,
  "Canberra": 0,
  "Castries": 0,
  "Chevrolet": 2,
  "China": 1,
  "Colombo": 0,
  "Colorado": 1,
  "Conakry": 0,
  "Concorde": 0,
  "Confucianism": 2,
  "Connecticut": 2,
  "Cordillera": 1,
  "Coxsackievirus": 0,
  "Crete": 0,
  "Crocs": 0,
  "Darwinism": 0,
  "Delaware": 1,
  "Dodoma": 0,
  "Doha": 0,
  "Douban": 1,
  "Dover": 1,
  "Edmond": 0,
  "Emanuel": 0,
  "England": 2,
  "English-Chinese": 1,
  "Ethernet": 1,
  "Facebook": 1,
  "Fahrenheit": 1,
  "Florence": 0,
  "Florida": 1,
  "Formosa": 0,
  "France": 1,
  "Freetown": 0,
  "Friday": 1,
  "G7": 1,
  "GATT": 0,
  "Gatsby": 2,
  "Gautama": 0,
  "Georgia": 1,
  "God": 0,
  "Godhead": 0,
  "Goliath": 0,
  "Gomorrah": 0,
  "Greenland": 1,
  "Greenwich": 1,
  "Grenada": 1,
  "Guantanamo": 0,
  "Guanyin": 3,
  "Gujarat": 0,
  "Gundam": 0,
  "Guyana": 1,
  "Gypsy": 0,
  "HK": 0,
  "Hades": 3,
  "Hamhung": 0,
  "Hawaii": 1,
  "Heidelberg": 1,
  "Himalayas": 1,
  "Hobart": 0,
  "Honiara": 0,
  "Houston": 0,
  "Hualinbu": 2,
  "Hyundai": 1,
  "I": 2,
  "I-beam": 0,
  "Idaho": 1,
  "Illinois": 0,
  "Indiana": 1,
  "Indochina": 0,
  "Internet": 1,
  "Inuit": 2,
  "Iowa": 3,
  "Islam": 1,
  "Islamabad": 0,
  "JUSCO": 0,
  "Judea": 0,
  "Kansas": 1,
  "Kentucky": 1,
  "Ketagalan": 1,
  "Kevlar": 0,
  "Kigali": 0,
  "Kinshasa": 0,
  "Kiribati": 0,
  "Kyrgyzstan": 2,
  "Kyōdō": 2,
  "Königsberg": 2,
  "Laos": 2,
  "Libreville": 0,
  "Lilongwe": 0,
  "Ljubljana": 0,
  "Louisiana": 1,
  "Luilang": 0,
  "Lusaka": 0,
  "Luxor": 0,
  "Lycopene": 0,
  "Madagascar": 1,
  "Maine": 1,
  "Malaysia": 3,
  "Malé": 0,
  "Managua": 0,
  "Manama": 0,
  "Manichaeism": 0,
  "Manjushri": 0,
  "Maoism": 2,
  "Maputo": 0,
  "Marxism-Leninism": 1,
  "Maryland": 1,
  "Massachusetts": 1,
  "Mesopotamia": 2,
  "Michigan": 1,
  "Minnesota": 1,
  "Mississippi": 1,
  "Missouri": 1,
  "Mogadishu": 2,
  "Monday": 1,
  "Mongolia": 1,
  "Montana": 1,
  "Montevideo": 2,
  "Montreal": 1,
  "Moroni": 0,
  "Nagoya": 1,
  "Nairobi": 1,
  "Nassau": 0,
  "Nauru": 1,
  "Nebraska": 1,
  "Netflix": 2,
  "Nevada": 1,
  "Nicosia": 0,
  "Nip": 2,
  "Nivea": 0,
  "Noah": 2,
  "Normandy": 1,
  "Nouakchott": 0,
  "Nuku'alofa": 0,
  "Oceanus": 0,
  "Odonata": 1,
  "Odysseus": 1,
  "Ohio": 1,
  "Oklahoma": 0,
  "Oregon": 1,
  "PTSD": 0,
  "Pandora": 1,
  "Paramaribo": 0,
  "Parmesan": 0,
  "Patricia": 0,
  "Pennsylvania": 1,
  "Pentecost": 1,
  "PhD": 1,
  "Philip": 2,
  "Podgorica": 0,
  "Polynesia": 0,
  "Potsdam": 0,
  "Praia": 0,
  "Pretoria": 0,
  "Protestantism": 2,
  "Pyongyang": 1,
  "Reykjavik": 0,
  "Rhone": 0,
  "Riyadh": 0,
  "Rochester": 0,
  "Russia": 3,
  "Sacramento": 0,
  "Samantabhadra": 0,
  "Samarkand": 2,
  "Sana'a": 0,
  "Sardinia": 0,
  "Saturday": 2,
  "Shennongjialin": 0,
  "Sherpa": 1,
  "Sina": 1,
  "Singapore": 4,
  "Skopje": 0,
  "Sodom": 0,
  "Sohu": 1,
  "Sumbawa": 0,
  "Sunday": 2,
  "Suriname": 2,
  "Sydney": 1,
  "Syracuse": 0,
  "T-shirt": 0,
  "Tahiti": 0,
  "Taichung": 1,
  "Tangun": 1,
  "Tasmania": 0,
  "Tegucigalpa": 0,
  "Tennessee": 1,
  "Tesco": 0,
  "Texas": 1,
  "Thimphu": 0,
  "Thursday": 1,
  "Tonga": 0,
  "Torobiawan": 0,
  "Transcaucasia": 0,
  "Tuesday": 1,
  "Tutankhamen": 1,
  "Tuvalu": 0,
  "Tw": 0,
  "UNESCO": 2,
  "USA": 1,
  "Utah": 1,
  "Utrecht": 0,
  "Vaduz": 0,
  "Valletta": 0,
  "Vanuatu": 0,
  "Vermont": 0,
  "Vientiane": 0,
  "Virginia": 0,
  "Vivien": 0,
  "Wa": 0,
  "Wednesday": 1,
  "Wi-Fi": 1,
  "Wimbledon": 0,
  "Wisconsin": 0,
  "Wyoming": 1,
  "Yokkaichi": 0,
  "Yunnan": 0,
  "Zhouzhuang": 1,
  "Zoroaster": 1,
  "Zoroastrianism": 2,
  "aardvark": 0,
  "abalone": 0,
  "abbot": 0,
  "abbreviation": 1,
  "abnormal": 1,
  "absorbent": 0,
  "abundant": 1,
  "abyss": 2,
  "accessible": 0,
  "accomplice": 1,
  "account": 0,
  "accountability": 0,
  "accurate": 0,
  "acne": 0,
  "acorn": 0,
  "activist": 0,
  "acute": 0,
  "additive": 0,
  "adjective": 1,
  "adolescence": 2,
  "advantageous": 2,
  "adventurer": 2,
  "aerobics": 3,
  "aerosol": 1,
  "aesthetics": 2,
  "affectation": 0,
  "affidavit": 0,
  "afternoon": 2,
  "again": 0,
  "agar": 0,
  "aged": 0,
  "agent": 0,
  "agoraphobia": 0,
  "agraphia": 0,
  "aide-de-camp": 0,
  "airtight": 2,
  "al-Qaeda": 1,
  "albinism": 1,
  "albumin": 0,
  "albuterol": 0,
  "alder": 0,
  "algae": 2,
  "alkalinity": 0,
  "alkane": 1,
  "alley": 1,
  "allosaurus": 0,
  "ally": 1,
  "almanac": 0,
  "almost": 2,
  "alone": 3,
  "already": 1,
  "altogether": 1,
  "alum": 0,
  "always": 1,
  "amateur": 1,
  "amber": 2,
  "ambience": 2,
  "ambitious": 0,
  "amenorrhoea": 0,
  "amethyst": 1,
  "ammeter": 2,
  "amnesia": 1,
  "amniocentesis": 0,
  "amplitude": 1,
  "amusement": 0,
  "amygdala": 0,
  "anaerobic": 0,
  "anchor": 2,
  "anchovy": 0,
  "and": 0,
  "anemia": 2,
  "anesthetic": 2,
  "anger": 2,
  "angiography": 0,
  "angler": 1,
  "anglerfish": 0,
  "angry": 0,
  "ankle": 1,
  "anorexia": 2,
  "ant": 1,
  "anthology": 2,
  "anti-aliasing": 2,
  "anti-corruption": 1,
  "anti-intellectual": 1,
  "anti-intellectualism": 1,
  "anti-missile": 0,
  "antibacterial": 0,
  "antibiotic": 1,
  "antidepressant": 0,
  "antidote": 1,
  "antihistamine": 0,
  "antisemitism": 1,
  "anus": 3,
  "anvil": 2,
  "ape": 3,
  "apostrophe": 1,
  "appearance": 3,
  "applause": 0,
  "appropriate": 0,
  "aquaculture": 0,
  "arbovirus": 0,
  "arc": 1,
  "archaeologist": 1,
  "arena": 0,
  "aristocracy": 3,
  "arm": 0,
  "armband": 0,
  "armor": 6,
  "armpit": 2,
  "army": 0,
  "aromatherapy": 0,
  "arrhythmia": 2,
  "arrogance": 1,
  "arrogant": 5,
  "arsenic": 0,
  "arsine": 0,
  "arsphenamine": 0,
  "asbestos": 1,
  "ashamed": 9,
  "ashes": 1,
  "ashtray": 1,
  "asparagus": 3,
  "aspiration": 0,
  "assistant": 4,
  "asthma": 1,
  "astonished": 0,
  "astonishing": 2,
  "astrologer": 2,
  "astrology": 2,
  "astronaut": 2,
  "astronomy": 2,
  "astrophysics": 1,
  "astute": 2,
  "asynchronous": 1,
  "atmosphere": 2,
  "attendant": 0,
  "audience": 0,
  "auntie": 0,
  "autism": 2,
  "automobile": 0,
  "autonomy": 0,
  "autopsy": 1,
  "avaricious": 0,
  "awkward": 2,
  "awning": 0,
  "azure": 3,
  "baby": 1,
  "bachelor": 1,
  "backboard": 0,
  "backbone": 2,
  "backhoe": 0,
  "backward": 2,
  "badge": 2,
  "badger": 1,
  "bag": 2,
  "baguette": 0,
  "baker": 1,
  "bakery": 1,
  "bamboo": 0,
  "band-aid": 2,
  "bandit": 3,
  "bank": 0,
  "banking": 1,
  "banner": 0,
  "banquet": 2,
  "barber": 2,
  "barbershop": 0,
  "barcode": 1,
  "barge": 2,
  "barley": 1,
  "barometer": 2,
  "barracuda": 0,
  "barrier": 1,
  "basin": 0,
  "basket": 4,
  "bassoon": 0,
  "bastard": 2,
  "bathtub": 2,
  "battle-ax": 1,
  "battlefield": 1,
  "battleship": 2,
  "bayonet": 0,
  "beam": 1,
  "beautiful": 9,
  "beaver": 0,
  "bedbug": 1,
  "bedding": 0,
  "bedrock": 1,
  "bedroom": 0,
  "bedside": 2,
  "beech": 0,
  "beehive": 2,
  "beeswax": 1,
  "beetle": 1,
  "beggar": 1,
  "believer": 2,
  "bellwether": 1,
  "belly": 0,
  "bench": 2,
  "bends": 0,
  "beneficiary": 0,
  "benefit": 0,
  "betel": 0,
  "beverage": 2,
  "bewildered": 0,
  "bidet": 0,
  "big": 0,
  "bigamy": 1,
  "bigwig": 0,
  "bilateral": 2,
  "bilirubin": 1,
  "billboard": 1,
  "biochemistry": 3,
  "biodiversity": 3,
  "biomass": 0,
  "biopsy": 0,
  "biotechnology": 0,
  "birch": 1,
  "bird": 4,
  "birdlime": 0,
  "birds": 3,
  "birdwatching": 1,
  "birthday": 1,
  "bison": 0,
  "bizarre": 0,
  "black": 2,
  "blackcurrant": 0,
  "blackmail": 1,
  "bladder": 0,
  "bleach": 1,
  "bleak": 0,
  "blind": 1,
  "blindness": 0,
  "block": 0,
  "blood": 2,
  "bloodstain": 1,
  "blouse": 0,
  "blowfish": 1,
  "blueberry": 2,
  "boa": 1,
  "boat": 1,
  "bony": 1,
  "bookcase": 0,
  "bookend": 0,
  "boomerang": 2,
  "boots": 2,
  "bottom": 2,
  "bottom-up": 2,
  "boulder": 1,
  "boundary": 3,
  "boundless": 2,
  "bowstring": 1,
  "boxer": 2,
  "boxing": 1,
  "boy": 1,
  "boyfriend": 2,
  "bra": 2,
  "bracelet": 1,
  "braces": 2,
  "bracket": 2,
  "braid": 2,
  "braille": 1,
  "brains": 0,
  "brake": 1,
  "bran": 0,
  "branch": 0,
  "brave": 3,
  "brazen": 0,
  "breadcrumbs": 0,
  "breadth": 1,
  "breastfeeding": 2,
  "breasts": 0,
  "brick": 3,
  "bride": 1,
  "bridegroom": 1,
  "bridge": 0,
  "bridle": 2,
  "brief": 0,
  "bright": 0,
  "brilliant": 0,
  "broad": 0,
  "broadband": 1,
  "broccoli": 4,
  "broker": 0,
  "broom": 3,
  "brothel": 0,
  "brown": 1,
  "bruise": 0,
  "brunch": 1,
  "brutal": 1,
  "bucktooth": 2,
  "bugle": 2,
  "built-in": 2,
  "bulimia": 0,
  "bull": 1,
  "bulldog": 0,
  "bulldozer": 1,
  "bullet": 1,
  "bumblebee": 0,
  "bunion": 0,
  "butcher": 1,
  "buttermilk": 0,
  "button": 2,
  "buyer": 2,
  "cabbage": 2,
  "cable": 0,
  "cake": 1,
  "calamity": 1,
  "calf": 1,
  "calipers": 1,
  "callus": 0,
  "calm": 0,
  "camellia": 1,
  "camp": 2,
  "campus": 2,
  "canal": 2,
  "cancer": 1,
  "cannibalism": 1,
  "cannot": 1,
  "canopy": 0,
  "canthus": 0,
  "capillary": 0,
  "caraway": 0,
  "carbohydrate": 1,
  "cardboard": 2,
  "cardigan": 1,
  "carefree": 0,
  "careful": 0,
  "careless": 0,
  "cargo": 0,
  "carnage": 0,
  "carnival": 2,
  "carnivore": 1,
  "carnivorous": 1,
  "carp": 2,
  "carry": 0,
  "cash": 2,
  "cask": 2,
  "catalysis": 1,
  "catalyst": 1,
  "category": 0,
  "caterpillar": 1,
  "catfish": 2,
  "cathedral": 1,
  "catwalk": 0,
  "cauliflower": 1,
  "cave": 0,
  "celebration": 1,
  "cellar": 1,
  "cellulite": 0,
  "cemetery": 1,
  "census": 1,
  "centigram": 2,
  "centipede": 3,
  "centrifuge": 2,
  "ceremony": 2,
  "certainly": 0,
  "certificate": 0,
  "cervix": 2,
  "chain": 2,
  "chakra": 0,
  "character": 0,
  "charming": 0,
  "charter": 0,
  "chattering": 2,
  "cheek": 4,
  "cheerful": 2,
  "cheese": 1,
  "cheesecake": 2,
  "chemicals": 1,
  "chemistry": 0,
  "chemotherapy": 2,
  "cherry": 2,
  "chest": 1,
  "chestnut": 2,
  "chewiness": 1,
  "chick": 2,
  "child": 8,
  "childhood": 3,
  "children": 1,
  "chimney": 1,
  "chin": 1,
  "chip": 1,
  "chiropractic": 0,
  "chisel": 0,
  "chitin": 2,
  "chivalry": 2,
  "chive": 0,
  "cholera": 2,
  "chubby": 1,
  "cicada": 0,
  "cinema": 1,
  "cinnabar": 0,
  "circumcision": 2,
  "circumstances": 1,
  "circus": 2,
  "city": 2,
  "clam": 2,
  "clamor": 0,
  "clarinet": 0,
  "class": 0,
  "clause": 1,
  "claustrophobia": 2,
  "clay": 2,
  "clean": 1,
  "clear": 3,
  "clenbuterol": 0,
  "clever": 2,
  "cliff": 2,
  "clindamycin": 0,
  "clitoris": 2,
  "cloakroom": 2,
  "clock": 1,
  "closed": 0,
  "clothes-horse": 0,
  "clothesline": 1,
  "clumsy": 2,
  "coach": 0,
  "cobble": 1,
  "coccyx": 0,
  "cock": 1,
  "cockroach": 2,
  "cod": 0,
  "code": 1,
  "coffin": 2,
  "colander": 0,
  "cold": 1,
  "collar": 0,
  "colleague": 1,
  "collect": 0,
  "columbarium": 0,
  "comet": 2,
  "commander": 2,
  "commander-in-chief": 1,
  "commentator": 2,
  "commission": 1,
  "community": 1,
  "companion": 2,
  "comparable": 1,
  "compass": 4,
  "compatible": 1,
  "compendium": 0,
  "compensation": 2,
  "competitive": 0,
  "completely": 4,
  "complexion": 2,
  "complicated": 2,
  "component": 0,
  "compost": 1,
  "computing": 0,
  "concubine": 0,
  "cone": 1,
  "confession": 2,
  "confused": 1,
  "congenial": 1,
  "conical": 2,
  "conjunction": 2,
  "connectionism": 0,
  "consanguinity": 0,
  "conscience": 2,
  "consonant": 2,
  "constable": 2,
  "constipation": 0,
  "constrained": 0,
  "continuous": 1,
  "contractor": 2,
  "contrail": 0,
  "contrary": 0,
  "convenient": 0,
  "convexity": 2,
  "cooking": 2,
  "coordinator": 2,
  "coprolite": 0,
  "copyright": 2,
  "coral": 2,
  "coriander": 0,
  "cork": 2,
  "cornea": 1,
  "corpse": 2,
  "corrigenda": 1,
  "corruption": 1,
  "cost": 0,
  "costume": 0,
  "couch": 0,
  "council": 1,
  "counter": 0,
  "countless": 1,
  "county": 1,
  "coupon": 1,
  "courage": 1,
  "courageous": 1,
  "courier": 1,
  "courtyard": 4,
  "coverage": 1,
  "coward": 4,
  "cowardly": 1,
  "crab": 2,
  "cranberry": 0,
  "crane": 0,
  "crate": 1,
  "crayfish": 0,
  "crazy": 1,
  "creationism": 0,
  "creativity": 0,
  "creator": 1,
  "creditor": 2,
  "credulous": 0,
  "cretinism": 0,
  "crevasse": 0,
  "cricket": 0,
  "criminal": 4,
  "crimson": 3,
  "croissant": 2,
  "crooked": 2,
  "crossbow": 1,
  "crossword": 1,
  "crotch": 2,
  "croupier": 1,
  "crowbar": 1,
  "crucible": 2,
  "cruelty": 1,
  "crust": 1,
  "crustacean": 2,
  "crystal": 2,
  "crystalline": 2,
  "cuckoo": 2,
  "culottes": 1,
  "culprit": 1,
  "cumbersome": 0,
  "cupidity": 0,
  "curb": 1,
  "curtain": 5,
  "custard": 0,
  "custom": 0,
  "customary": 0,
  "cuttlefish": 1,
  "cyberspace": 1,
  "cytoplasm": 1,
  "dagger": 1,
  "dam": 2,
  "dancer": 1,
  "dancing": 0,
  "dark": 0,
  "dataset": 2,
  "daughter-in-law": 1,
  "dawdling": 0,
  "dawn": 3,
  "daytime": 1,
  "dazed": 0,
  "deadline": 2,
  "deaf": 2,
  "dealer": 0,
  "debtor": 0,
  "decagon": 2,
  "decagram": 2,
  "deceitful": 0,
  "deciliter": 2,
  "decimeter": 2,
  "decoder": 1
}